vbao/__init__.py
vbao/base.py
vbao/config.py
vbao/convenient_class.py
vbao/core/__init__.py
vbao/core/core.py
vbao/core/mixin.py
vbao_MVVM-0.3.dist-info/LICENSE
vbao_MVVM-0.3.dist-info/METADATA
vbao_MVVM-0.3.dist-info/WHEEL
vbao_MVVM-0.3.dist-info/top_level.txt
vbao_MVVM-0.3.dist-info/RECORD
