Metadata-Version: 2.1
Name: vbao_MVVM
Version: 0.3
Summary: A library aiming for building an MVVM (or MVFM) project
Author: Meidozuki
Project-URL: Homepage, https://github.com/Meidozuki/VBAO
Project-URL: Bug Tracker, https://github.com/Meidozuki/VBAO/issues
Classifier: Programming Language :: Python :: 3
Classifier: License :: OSI Approved :: GNU Library or Lesser General Public License (LGPL)
Classifier: Operating System :: OS Independent
Requires-Python: >=3.7
License-File: LICENSE
